tfignite/__init__.py
tfignite/callbacks.py
tfignite/dataset.py
tfignite/engine.py
tfignite/model.py
tfignite/parser.py
tfignite/util.py
tfignite-0.0.4.dist-info/LICENSE
tfignite-0.0.4.dist-info/METADATA
tfignite-0.0.4.dist-info/WHEEL
tfignite-0.0.4.dist-info/top_level.txt
tfignite-0.0.4.dist-info/RECORD
