Metadata-Version: 2.1
Name: tfignite
Version: 0.0.4
Summary: Hight level training routine for tensorflow.
Home-page: https://github.com/ipod825/tfignite
Author: Shih-Ming Wang
Author-email: swang150@ucsc.edu
License: UNKNOWN
Download-URL: https://github.com/ipod825/tfignite/tarball/0.0.1
Platform: UNKNOWN
Classifier: Programming Language :: Python :: 3
Classifier: License :: OSI Approved :: MIT License
Classifier: Operating System :: OS Independent
